rapidocr/__init__.py
rapidocr/cli.py
rapidocr/config.yaml
rapidocr/default_models.yaml
rapidocr/main.py
rapidocr/cal_rec_boxes/__init__.py
rapidocr/cal_rec_boxes/main.py
rapidocr/ch_ppocr_cls/__init__.py
rapidocr/ch_ppocr_cls/main.py
rapidocr/ch_ppocr_cls/utils.py
rapidocr/ch_ppocr_det/__init__.py
rapidocr/ch_ppocr_det/main.py
rapidocr/ch_ppocr_det/utils.py
rapidocr/ch_ppocr_rec/__init__.py
rapidocr/ch_ppocr_rec/main.py
rapidocr/ch_ppocr_rec/typings.py
rapidocr/ch_ppocr_rec/utils.py
rapidocr/inference_engine/__init__.py
rapidocr/inference_engine/base.py
rapidocr/inference_engine/openvino.py
rapidocr/inference_engine/onnxruntime/__init__.py
rapidocr/inference_engine/onnxruntime/main.py
rapidocr/inference_engine/onnxruntime/provider_config.py
rapidocr/inference_engine/paddle/__init__.py
rapidocr/inference_engine/paddle/device_config.py
rapidocr/inference_engine/paddle/main.py
rapidocr/inference_engine/pytorch/__init__.py
rapidocr/inference_engine/pytorch/device_config.py
rapidocr/inference_engine/pytorch/main.py
rapidocr/inference_engine/pytorch/networks/__init__.py
rapidocr/inference_engine/pytorch/networks/arch_config.yaml
rapidocr/inference_engine/pytorch/networks/common.py
rapidocr/inference_engine/pytorch/networks/main.py
rapidocr/inference_engine/pytorch/networks/architectures/__init__.py
rapidocr/inference_engine/pytorch/networks/architectures/base_model.py
rapidocr/inference_engine/pytorch/networks/backbones/__init__.py
rapidocr/inference_engine/pytorch/networks/backbones/det_mobilenet_v3.py
rapidocr/inference_engine/pytorch/networks/backbones/rec_donut_swin.py
rapidocr/inference_engine/pytorch/networks/backbones/rec_hgnet.py
rapidocr/inference_engine/pytorch/networks/backbones/rec_lcnetv3.py
rapidocr/inference_engine/pytorch/networks/backbones/rec_mobilenet_v3.py
rapidocr/inference_engine/pytorch/networks/backbones/rec_mv1_enhance.py
rapidocr/inference_engine/pytorch/networks/backbones/rec_pphgnetv2.py
rapidocr-3.5.0.dist-info/METADATA
rapidocr-3.5.0.dist-info/WHEEL
rapidocr-3.5.0.dist-info/entry_points.txt
rapidocr-3.5.0.dist-info/top_level.txt
rapidocr-3.5.0.dist-info/RECORD
